{
  "id": "43d97f2bec95b60d",
  "title": "Agent-driven development in Copilot Applied Science",
  "url": "https://github.blog/ai-and-ml/github-copilot/agent-driven-development-in-copilot-applied-science/",
  "source": "GitHub Blog",
  "type": "article",
  "description": "I used coding agents to build agents that automated part of my job. Here's what I learned about working better with coding agents. The post Agent-driven development in Copilot Applied Science appeared first on The GitHub Blog.",
  "tags": [
    "dev",
    "ai & ml",
    "application development",
    "architecture & optimization",
    "github copilot"
  ],
  "published_at": "2026-03-31T16:00:00.000Z",
  "feed_id": "githublog"
}
