{
  "id": "e07e8af35a3b9a56",
  "title": "Your coding agent doesn't need more autonomy. It needs a manager.",
  "url": "https://dev.to/overcast_27b5101f0609c684/your-coding-agent-doesnt-need-more-autonomy-it-needs-a-manager-2b76",
  "source": "Dev.to",
  "type": "article",
  "tags": [
    "dev",
    "ai",
    "agents",
    "devtools",
    "programming"
  ],
  "published_at": "2026-06-01T19:14:16.000Z",
  "feed_id": "devto",
  "description": "## 개요\n\n코딩 에이전트의 능력 향상에 초점이 맞춰져 있었지만, 이제는 에이전트의 출력을 제어하고 신뢰도를 높이는 관리 계층이 필요합니다.\n\n## 주요 내용\n\n*   **현실 코드베이스 적용 시 문제점:** 유능해 보이는 코딩 에이전트도 일정 시간이 지나면 예상치 못한 광범위한 코드 변경, 존재하지 않는 인터페이스 생성 등 통제되지 않은 행동을 보여 사람이 직접 수정하는 것보다 더 많은 비용을 초래합니다.\n*   **기존 개발의 성공 요인:** 인간 주니어 엔지니어의 경우, 명확한 업무 범위 설정, 코드 리뷰, 아키텍처 규칙 적용 등 시스템적인 통제 메커니즘을 통해 신뢰를 구축하고 업무를 확장합니다.\n*   **에이전트 운영 프로토콜 (AOP)의 필요성:** 코딩 에이전트의 능력을 실제 프로젝트에 안전하고 신뢰할 수 있게 적용하기 위해, 인간 팀원에게 적용하는 것과 유사한 통제 및 관리 계층이 필요합니다.\n*   **AOP의 핵심 기능:**\n    *   **범위(Scope) 강제:** 에이전트가 접근하고 변경할 수 있는 코드 범위를 사전에 정의하고 이를 위반하는 경우 즉시 감지합니다.\n    *   **적합성(Conformance) 실행:** 시스템 아키텍처 규칙을 테스트 스위트처럼 실행하여 에이전트 출력의 규칙 준수 여부를 검증합니다.\n    *   **격리된 검토(Review) 제공:** 코드 작성자와 코드 승인자를 분리하여 실수를 사전에 방지합니다.\n    *   **단계 간 계약(Contracts between steps):** 작업 흐름을 타입화되고 검사 가능한 핸드오프를 통해 진행하여 문제 발생 지점을 명확히 파악합니다.\n    *   **감사 추적(Audit trail):** 모든 결정 과정을 기록하여 사후 검증이 가능하게 합니다.\n*   **사고방식의 전환:** 코딩 에이전트를 즉흥적인 해결사가 아닌, 반드시 보호 장치가 필요한 빠르게 성장하는 주니어 엔지니어로 인식해야 합니다.\n\n## 시사점\n\n차세대 에이전트 엔지니어링 경쟁에서 승리하기 위해서는 최고의 모델 자체보다, 그 능력을 예측 가능하고 검토 가능하며 확장 가능한 방식으로 배포할 수 있는 제어 계층을 구축하는 것이 중요합니다."
}
