{
  "id": "b9b14eacb3604485",
  "title": "Firefox is working on a rounded redesign with easy-to-find controls for privacy and AI",
  "url": "https://www.theverge.com/tech/935631/firefox-project-nova-redesign",
  "source": "The Verge",
  "type": "article",
  "tags": [
    "tech"
  ],
  "published_at": "2026-05-21T20:05:09.000Z",
  "feed_id": "theverge",
  "description": "## 개요\n\nFirefox는 올해 말부터 적용될 예정인 \"Project Nova\"라는 이름의 대대적인 비주얼 개편을 통해 개인 정보 보호 설정과 AI 기능 접근성을 향상시키고 있습니다.\n\n## 주요 내용\n\n*   **Project Nova의 디자인 개편:**\n    *   전반적으로 둥근 UI 요소와 버블 형태의 탭, 새로워진 불꽃 모티브 색상 팔레트를 적용합니다.\n    *   라이트 및 다크 테마 모두에서 시각적으로 일관된 아이콘을 업데이트합니다.\n    *   툴바와 탭이 더욱 둥글게 디자인됩니다.\n*   **AI 기능 접근성 강화:**\n    *   설정에서 AI 기능의 완전 차단 여부와 관계없이, AI 기능 및 모델은 사용자가 선택하기 전까지 컴퓨터에 다운로드되지 않습니다.\n    *   설치된 AI 기능 목록과 차지하는 공간을 Chrome보다 쉽게 확인할 수 있습니다.\n*   **새로운 기능 및 생산성 향상:**\n    *   Web Serial API를 지원하여 웹사이트가 네이티브 애플리케이션이나 설치 프로그램 없이 장치를 제어하거나 펌웨어를 제공할 수 있게 됩니다. (Firefox 151에 포함)\n    *   Firefox Home 페이지 디자인 업데이트, 새로운 배경화면, 브라우저 PDF 뷰어에서 여러 PDF 병합 기능이 Firefox 151에 추가되었습니다.\n    *   이전의 컴팩트 모드를 복원하여 앞으로 가기/뒤로 가기 버튼과 같은 브라우저 컨트롤을 압축합니다.\n    *   탭 그룹, 분할 보기, 세로 탭에 대한 접근성을 용이하게 합니다.\n*   **개인화 및 커스터마이징:**\n    *   새로운 배경화면과 테마를 통해 브라우저 창 전체에 적용되는 라이트 및 다크 모드 색상 테마를 제공합니다.\n    *   탭 및 기타 UI 요소의 모양을 제어하는 기능도 탐색 중입니다.\n\n## 시사점\n\nFirefox의 \"Project Nova\" 개편은 사용자 경험을 현대화하고, 개인 정보 보호 및 AI 기능에 대한 통제력을 강화하며, 생산성 도구에 대한 접근성을 높여 브라우저의 경쟁력을 향상시킬 것으로 기대됩니다."
}
