{
  "id": "230e6b0b90453ca4",
  "title": "Report: US demands Reddit unmask ICE critic, summons firm to grand jury",
  "url": "https://arstechnica.com/tech-policy/2026/04/trump-admin-hounds-reddit-to-reveal-identity-of-user-who-criticized-ice/",
  "source": "Ars Technica",
  "type": "article",
  "description": "Trump admin reportedly gets grand jury involved in attempt to identify Redditor.",
  "tags": [
    "tech",
    "policy",
    "ice",
    "reddit"
  ],
  "published_at": "2026-04-10T18:43:25.000Z",
  "feed_id": "arstechnica"
}
