{
  "id": "3df0c970943f4ad6",
  "title": "Basta \"Blocco dello Scrittore\": Ho creato un Hub di 50+ Tool AI gratuiti per scrivere tutto (senza registrazione)",
  "url": "https://dev.to/andreatrotta1998dev/basta-blocco-dello-scrittore-ho-creato-un-hub-di-50-tool-ai-gratuiti-per-scrivere-tutto-senza-56a1",
  "source": "Dev.to",
  "type": "article",
  "tags": [
    "dev",
    "ai",
    "webdev",
    "writing",
    "tailwindcss"
  ],
  "published_at": "2026-04-22T15:07:45.000Z",
  "feed_id": "devto",
  "description": "## 개요\n\nTextyAI는 50개 이상의 무료 AI 기반 마이크로 툴을 제공하여 등록 없이 3초 안에 완벽한 텍스트를 생성하도록 돕는 웹 기반 허브입니다.\n\n## 주요 내용\n\n*   **개발 동기:** 개발자이자 매일 수십 개의 이메일을 관리하는 사람으로서, 공식적인 이메일 작성, 휴가 신청, 사직서 작성, 소셜 미디어 자기소개, 제품 설명 작성 등에서 발생하는 시간 낭비와 인지적 부담을 줄이기 위해 TextyAI를 개발했습니다.\n*   **TextyAI의 특징:**\n    *   50개 이상의 AI 기반 마이크로 툴을 제공합니다.\n    *   등록 절차가 필요 없습니다.\n    *   숨겨진 구독료가 없습니다.\n    *   복잡한 프롬프트 학습이 필요 없습니다.\n    *   단 두 단어 입력으로 3초 안에 결과물을 얻을 수 있습니다.\n*   **제공 툴 카테고리:**\n    *   **커리어 (Carriera):** 사직서, 연봉 인상 요청, 면접 후속 이메일 생성기.\n    *   **비즈니스 (Business):** 공식 이메일, 고객 응대, AI 기반 발표 자료 생성.\n    *   **소셜 미디어 (Social Media):** Instagram 캡션, TikTok 스크립트, 로봇 같지 않은 LinkedIn 게시물 생성.\n    *   **학생 (Studenti):** 교수님께 보내는 이메일(불안 없이), 논문 요청.\n*   **기술적 구현:**\n    *   Next.js와 Vercel을 사용하여 모든 페이지가 즉시 로드되도록 설계했습니다.\n    *   깨끗하고 콘텐츠 중심적인 사용자 경험(UX)에 집중했습니다.\n    *   현재 55개의 툴을 보유하고 있으며, 추가 툴 개발 중입니다.\n\n## 시사점\n\nTextyAI는 번거로운 텍스트 생성 과정을 자동화하여 사용자가 소중한 시간을 절약하고 프로젝트나 휴식에 더 집중할 수 있도록 지원합니다."
}
