{
  "id": "aae60583edfe380f",
  "title": "GitHub Universe is back: We want you to take the stage",
  "url": "https://github.blog/news-insights/company-news/github-universe-is-back-we-want-you-to-take-the-stage/",
  "source": "GitHub Blog",
  "type": "article",
  "description": "Get inspired by five of the most memorable, magical, and quirky Universe sessions to date. The post GitHub Universe is back: We want you to take the stage appeared first on The GitHub Blog.",
  "tags": [
    "dev",
    "company news",
    "news & insights",
    "github universe"
  ],
  "published_at": "2026-04-08T16:35:46.000Z",
  "feed_id": "githublog"
}
