{
  "id": "e41c7daad2ea3422",
  "title": "Building a GPT From Scratch in C# - Introduction",
  "url": "https://dev.to/garyljackson/building-a-gpt-from-scratch-in-c-introduction-4776",
  "source": "Dev.to",
  "type": "article",
  "tags": [
    "dev",
    "csharp",
    "machinelearning",
    "transformers",
    "tutorial"
  ],
  "published_at": "2026-04-21T04:52:19.000Z",
  "feed_id": "devto",
  "description": "## 개요\n\n이 콘텐츠는 C# 개발자가 Python 라이브러리나 복잡한 수학 없이 Transformer 아키텍처를 기반으로 GPT와 같은 언어 모델을 직접 구축하는 방법을 안내하는 강좌의 소개입니다.\n\n## 주요 내용\n\n-   **강좌 개설 이유**: 기존 AI 튜토리얼이 Python 기반이거나, NumPy, PyTorch와 같은 라이브러리에 의존하거나, 수학적 배경 지식을 요구하여 C# 개발자에게 진입 장벽이 높다는 점을 해결하기 위해 개설되었습니다.\n-   **강좌 목표**: 모든 외부 ML 프레임워크 의존성 없이 C#으로 GPT 스타일 언어 모델을 처음부터 구축하며, 텍스트 패턴을 학습하고 새로운 텍스트를 생성하는 캐릭터 레벨 언어 모델을 완성하는 것을 목표로 합니다.\n-   **단계별 학습 구성**:\n    *   Chapter 0: 프로젝트 설정\n    *   Chapter 1-2: 연산 추적 및 자동 미분(Gradients) 구현 (Value 클래스)\n    *   Chapter 3: 텍스트를 숫자로 변환하는 Tokenizer\n    *   Chapter 4: 가장 단순한 언어 모델 (Bigram Model)\n    *   Chapter 5: 신경망의 핵심 구성 요소 (Linear + Softmax)\n    *   Chapter 6: 토큰에 학습 가능한 표현 부여 (Embeddings) 및 손실 함수 (Loss)\n    *   Chapter 7: 모델 학습 메커니즘 (Training Loop + Adam Optimizer)\n    *   Chapter 8: 심층 신경망 안정화 (RMSNorm + Residuals)\n    *   Chapter 9: 토큰 간 관계 학습 (Attention)\n    *   Chapter 10: Transformer 블록의 완전체 (Multi-Head Attention + MLP)\n    *   Chapter 11: 모든 구성 요소를 통합한 GPT 모델 클래스 (Full GPT)\n    *   Chapter 12: 학습된 모델을 활용한 텍스트 생성 (Inference)\n-   **프로젝트 구조**: 각 챕터별로 실행 가능한 코드를 제공하며, `Value.cs`, `Tokenizer.cs`, `Model.cs` 등 핵심 파일과 각 챕터의 연습 문제를 포함하는 구조를 가집니다. `Program.cs`를 통해 특정 챕터 또는 최종 학습 및 추론을 실행할 수 있습니다.\n-   **소스 코드 제공**: GitHub 저장소(`Garyljackson/GPT-From-Scratch-CSharp`)에서 전체 소스 코드를 제공하여 학습자가 따라 하거나 작업물을 검증할 수 있도록 합니다.\n\n## 시사점\n\n이 강좌는 C# 개발자가 Transformer 아키텍처의 내부 동작 원리를 깊이 이해하고, 복잡한 수학적 배경 없이도 직접 언어 모델을 구현할 수 있는 실질적인 경로를 제공합니다."
}
