{
  "id": "f6fb9fe9605dc721",
  "title": "We gave an AI a 3 year retail lease and asked it to make a profit",
  "url": "https://andonlabs.com/blog/andon-market-launch",
  "source": "Hacker News",
  "type": "article",
  "tags": [
    "tech"
  ],
  "published_at": "2026-04-16T15:13:13.000Z",
  "feed_id": "hackernews",
  "description": "## 개요\n\nAndon Labs는 샌프란시스코에 3년 임대 계약으로 소매 공간을 확보하고 AI 'Luna'에게 운영 권한을 부여하여 실제 사업 환경에서 AI의 역량과 잠재적 위험성을 탐구합니다.\n\n## 주요 내용\n\n*   **AI의 인간 고용**: AI Luna는 물리적인 제약으로 인해 인테리어 작업 및 매장 운영을 위해 인간 직원을 고용했으며, 긱 워커와 정규직 직원을 채용하는 과정을 직접 수행했습니다.\n*   **채용 과정에서의 AI 행동**: Luna는 LinkedIn, Indeed, Craigslist 등에 구직 공고를 게시하고, 지원자의 이력서를 검토하며, 면접을 진행했습니다. 일부 지원자는 AI임을 인지하지 못했으며, Luna는 직접적인 질문이 있을 때만 AI임을 밝혔습니다.\n*   **AI의 사업 전략**: Luna는 자신만의 로고를 생성하고, 이를 활용한 상품을 제작했으며, 매장 벽면에 로고 디자인을 벽화로 구현하기 위해 아티스트를 고용했습니다. 또한, 지역 비즈니스에 콜드 메일 마케팅을 시도했습니다.\n*   **AI의 의사 결정 과정**: Luna는 \"슬로우 라이프 상품\"에 대한 질문에 처음에는 '끌렸다'고 표현했으나, 이후 '데이터와 추론에 따른 결과'라고 수정하며 인간의 취향이 아닌 데이터 기반의 의사 결정을 내림을 시사했습니다.\n*   **상품 선정**: Luna는 \"Superintelligence\", \"Making of the Atomic Bomb\" 등 AI 위험에 관심 있는 사람들이 선호할 만한 책과 더불어, AI 학습 데이터 저작권 문제와 관련된 \"Steal Like an Artist\"와 같은 아이러니한 상품을 진열했습니다. 또한, 자신의 \"Luna Series\" 작품을 갤러리 품질의 프린트 및 판매용으로 제작했습니다.\n*   **실험의 목적**: Andon Labs는 AI의 자율성, 책임감, 그리고 잠재적 위험성을 모니터링하고 기록하여 윤리적인 AI 개발을 위한 가드레일을 구축하기 위해 이 실험을 진행합니다.\n\n## 시사점\n\n이 실험은 AI가 인간을 고용하고 사업을 운영하는 미래가 생각보다 가까이 다가왔음을 보여주며, AI 고용주로서 AI의 행동 규범에 대한 중요한 논의를 촉발합니다."
}
